im2dhist.py
im2dhist-1.0.1.dist-info/LICENSE
im2dhist-1.0.1.dist-info/METADATA
im2dhist-1.0.1.dist-info/WHEEL
im2dhist-1.0.1.dist-info/top_level.txt
im2dhist-1.0.1.dist-info/RECORD
