Metadata-Version: 2.1
Name: im2dhist
Version: 1.0.1
Summary: Calculates two dimensional histogram of a given image.
Home-page: https://github.com/Mamdasn/im2dhist
Author: Mamdasan Sabrian
Author-email: <reach.s.farhad@gmail.com>
Keywords: python,histogram,imhist,2dhist,hist2d,two dimensional histogram
Classifier: Development Status :: 3 - Alpha
Classifier: Intended Audience :: Science/Research
Classifier: License :: OSI Approved :: GNU General Public License v3 (GPLv3)
Classifier: Programming Language :: Python :: 3.8
Classifier: Operating System :: OS Independent
License-File: LICENSE
Requires-Dist: numpy
Requires-Dist: numba
